cool_ip_api/__init__.py
cool_ip_api/main.py
cool_ip_api/provider/abstractapi_com.py
cool_ip_api/provider/ip_api_com.py
cool_ip_api/provider/ip_who_is_io.py
cool_ip_api/provider/ipapi_co.py
cool_ip_api/provider/ipapi_com.py
cool_ip_api/provider/ipify_org.py
cool_ip_api/provider/ipinfo_io.py
cool_ip_api/provider/myip_wtf.py
cool_ip_api/provider/resolver_abc.py
cool_ip_api/utils/errors.py
cool_ip_api-0.2.0.dist-info/entry_points.txt
cool_ip_api-0.2.0.dist-info/WHEEL
cool_ip_api-0.2.0.dist-info/METADATA
cool_ip_api-0.2.0.dist-info/RECORD
