Metadata-Version: 2.1
Name: cool-ip-api
Version: 0.2.0
Summary: A collections of wrapper for different IP info APIs
Home-page: https://github.com/sokripon/cool-ip-api
Keywords: ip,api,wrapper,ip-api,ipinfo,ipgeolocation,ipdata
Author: sokripon
Author-email: sokripon@gmail.com
Requires-Python: >=3.10,<4.0
Classifier: Programming Language :: Python :: 3
Classifier: Programming Language :: Python :: 3.10
Requires-Dist: httpx (>=0.23.0,<0.24.0)
Requires-Dist: pydantic (>=1.10.2,<2.0.0)
Requires-Dist: requests (>=2.28.1,<3.0.0)
Project-URL: Repository, https://github.com/sokripon/cool-ip-api
